_pylinearfold.cpython-314t-x86_64-linux-gnu.so
_pylinearpartition.cpython-314t-x86_64-linux-gnu.so
pylinearfold/__init__.py
pylinearfold/_pylinearfold.cpp
pylinearfold/_pylinearpartition.cpp
pylinearfold-0.2.1.dist-info/METADATA
pylinearfold-0.2.1.dist-info/WHEEL
pylinearfold-0.2.1.dist-info/RECORD
pylinearfold-0.2.1.dist-info/licenses/COPYING.md
pylinearfold-0.2.1.dist-info/licenses/LICENSE.md
