Metadata-Version: 2.4
Name: pylinearfold
Version: 0.2.1
Summary: Python bindings for LinearFold and LinearPartition
Maintainer-Email: Luca Monari <l.monari@zmbh.de>, Dominic Kempf <ssc@uni-heidelberg.de>
License-File: COPYING.md
License-File: LICENSE.md
Classifier: Programming Language :: Python :: 3
Classifier: Operating System :: OS Independent
Requires-Python: >=3.10
Requires-Dist: numpy
Provides-Extra: tests
Requires-Dist: pytest; extra == "tests"
